caep/__init__.py
caep/config.py
caep/example.py
caep/helpers.py
caep/py.typed
caep/schema.py
caep/xdg.py
caep-1.6.0.dist-info/METADATA
caep-1.6.0.dist-info/WHEEL
caep-1.6.0.dist-info/licenses/LICENSE
caep-1.6.0.dist-info/RECORD
