Metadata-Version: 2.4
Name: caep
Version: 1.6.0
Summary: Config Argument Env Parser (CAEP)
Project-URL: Homepage, https://github.com/mnemonic-no/caep
Author-email: mnemonic <opensource@mnemonic.no>
License-Expression: ISC
License-File: LICENSE
Classifier: Development Status :: 5 - Production/Stable
Classifier: License :: OSI Approved :: ISC License (ISCL)
Classifier: Topic :: Software Development :: Libraries :: Python Modules
Classifier: Typing :: Typed
Requires-Python: >=3.9
Requires-Dist: pydantic<3,>=1.10.0
